hdmi2usb/__init__.py
hdmi2usb/firmware/zero.bin
hdmi2usb/firmware/fx2/atlys/ixo-usb-jtag.hex
hdmi2usb/firmware/fx2/opsis/eeprom.ihx
hdmi2usb/firmware/fx2/opsis/ixo-usb-jtag.hex
hdmi2usb/firmware/fx2/opsis/usb-uart.ihx
hdmi2usb/firmware/spartan6/atlys/bscan_spi_xc6slx45.bit
hdmi2usb/firmware/spartan6/opsis/bscan_spi_xc6slx45t.bit
hdmi2usb/modeswitch/__init__.py
hdmi2usb/modeswitch/_version.py
hdmi2usb/modeswitch/base.py
hdmi2usb/modeswitch/boards.py
hdmi2usb/modeswitch/cli.py
hdmi2usb/modeswitch/files.py
hdmi2usb/modeswitch/libusb.py
hdmi2usb/modeswitch/lsusb.py
hdmi2usb/modeswitch/tests.py
hdmi2usb.modeswitch-0.0.0.post151.dist-info/DESCRIPTION.rst
hdmi2usb.modeswitch-0.0.0.post151.dist-info/METADATA
hdmi2usb.modeswitch-0.0.0.post151.dist-info/RECORD
hdmi2usb.modeswitch-0.0.0.post151.dist-info/WHEEL
hdmi2usb.modeswitch-0.0.0.post151.dist-info/entry_points.txt
hdmi2usb.modeswitch-0.0.0.post151.dist-info/metadata.json
hdmi2usb.modeswitch-0.0.0.post151.dist-info/top_level.txt
