Metadata-Version: 2.0
Name: hdmi2usb.modeswitch
Version: 0.0.0.post151
Summary: Module and command line tool for control the mode of HDMI2USB devices.
Home-page: https://hdmi2usb.tv
Author: TimVideos' HDMI2USB project
Author-email: hdmi2usb@googlegroups.com
License: Apache 2.0
Download-URL: https://github.com/timvideos/HDMI2USB-mode-switch
Keywords: HDL ASIC FPGA hardware design
Platform: Any
Classifier: Development Status :: 3 - Alpha
Classifier: Environment :: Console
Classifier: Intended Audience :: Developers
Classifier: License :: OSI Approved :: BSD License
Classifier: Operating System :: OS Independent
Classifier: Programming Language :: Python
Classifier: Programming Language :: Python :: 3 :: Only
Classifier: Topic :: Scientific/Engineering :: Electronic Design Automation (EDA)
